{
  "todos": [
    {
      "id": 1,
      "content": "Create React Appをインストールする",
      "done": true
    },
    {
      "id": 2,
      "content": "JSON Serverで仮のAPIを作成する",
      "done": false
    },
    {
      "id": 3,
      "content": "Chakra UIをインストールする",
      "done": false
    },
    {
      "content": "hoge",
      "id": "01FS98P1YBH1K9ESCAJTFW7JCY",
      "done": false
    },
    {
      "content": "fuga",
      "id": "01FS98PH6JPDZMME1XAY2QGWZY",
      "done": false
    },
    {
      "content": "piyo",
      "id": "01FS98PM95S8VJVFPFKHY30HW9",
      "done": false
    }
  ]
}